{
  "fill-specializations" : [
    {
      "value" : {
        "linear-gradient" : [
          "display-p3:0.15858,0.27026,0.42576,1.00000",
          "display-p3:0.09966,0.23329,0.44631,1.00000"
        ],
        "orientation" : {
          "start" : {
            "x" : 0.5,
            "y" : 0
          },
          "stop" : {
            "x" : 0.5,
            "y" : 0.7
          }
        }
      }
    },
    {
      "appearance" : "dark",
      "value" : {
        "linear-gradient" : [
          "display-p3:0.04826,0.08225,0.12957,1.00000",
          "display-p3:0.09383,0.21859,0.40959,1.00000"
        ],
        "orientation" : {
          "start" : {
            "x" : 0.5,
            "y" : 0
          },
          "stop" : {
            "x" : 0.5,
            "y" : 0.7
          }
        }
      }
    }
  ],
  "groups" : [
    {
      "layers" : [
        {
          "image-name" : "fluster_symbol.svg",
          "name" : "fluster_symbol",
          "position" : {
            "scale" : 3,
            "translation-in-points" : [
              -1.499985781408327,
              0.17849999999998545
            ]
          }
        }
      ],
      "shadow" : {
        "kind" : "neutral",
        "opacity" : 0.5
      },
      "translucency" : {
        "enabled" : true,
        "value" : 0.5
      }
    }
  ],
  "supported-platforms" : {
    "circles" : [
      "watchOS"
    ],
    "squares" : "shared"
  }
}